mailto_uri/__init__.py
mailto_uri/cli.py
mailto_uri-1.2.0.dist-info/LICENSE
mailto_uri-1.2.0.dist-info/METADATA
mailto_uri-1.2.0.dist-info/WHEEL
mailto_uri-1.2.0.dist-info/entry_points.txt
mailto_uri-1.2.0.dist-info/top_level.txt
mailto_uri-1.2.0.dist-info/RECORD
