Metadata-Version: 2.1
Name: mailto-uri
Version: 1.2.0
Summary: create mailto URIs
Home-page: https://github.com/idiv-biodiversity/mailto-uri
Author: Christian Krause
Author-email: christian.krause@idiv.de
License: UNKNOWN
Platform: UNKNOWN
Classifier: Programming Language :: Python :: 3
Classifier: License :: OSI Approved :: GNU General Public License v3 or later (GPLv3+)
Classifier: Operating System :: OS Independent
Requires-Dist: argparse
Requires-Dist: python-frontmatter
